tassadar/__init__.py
tassadar/callback.py
tassadar/coordinator.py
tassadar/engine.py
tassadar/proxy.py
tassadar/scheduler.py
tassadar-0.1.0.dist-info/METADATA
tassadar-0.1.0.dist-info/WHEEL
tassadar-0.1.0.dist-info/RECORD
